llm_azure_ai/__init__.py
llm_azure_ai/ai_inference.py
llm_azure_ai/openai.py
llm_azure_ai/py.typed
llm_azure_ai-0.1.0a0.dist-info/METADATA
llm_azure_ai-0.1.0a0.dist-info/WHEEL
llm_azure_ai-0.1.0a0.dist-info/entry_points.txt
llm_azure_ai-0.1.0a0.dist-info/RECORD
